{
    "2026-05-27 09:39:08": {
        "timestamp": "2026-05-27 09:39:08",
        "instrument_id": "69df6e21bab8e09015512d21",
        "instrument_name": "NGAS(COMEXMAY-MCXMAY)MAYDG",
        "badla_type": "GAS",
        "room_id": "BzG7h",
        "raw_data": {
            "roomId": "BzG7h",
            "data": [
                {
                    "mode": "KT",
                    "ExchangeToken": "488505",
                    "instrument_token": "68609638792",
                    "tradable": true,
                    "last_price": 279.7,
                    "last_quantity": 1,
                    "average_price": "281.15",
                    "volume": 8767,
                    "buy_quantity": 300,
                    "sell_quantity": 2352,
                    "ohlc_open": "279.9",
                    "ohlc_high": "285.3",
                    "ohlc_low": "278.4",
                    "ohlc_close": "277.5",
                    "change": "0",
                    "buy_price_0": 279.7,
                    "sell_price_0": 279.8,
                    "buy_qty_0": 3155,
                    "sell_qty_0": 3155,
                    "LastTradeTimeD": "2026-05-26T23:29:55",
                    "last_trade_time": "26-05-2026 23:29:55",
                    "oi": 3160,
                    "oi_day_high": 4758,
                    "oi_day_low": 3160,
                    "timestamp": "2026-05-26T23:30:00",
                    "name": "NATURALGAS",
                    "expiry": "26-05-2026",
                    "exchange": "MCX",
                    "tradingsymbol": "NATURALGAS26MAYFUT",
                    "lot_size": "1.000",
                    "lower_circuit": "266.4",
                    "upper_circuit": "288.6",
                    "net_change": "2.2",
                    "percentage_change": "0.79",
                    "buy": [
                        {
                            "Quantity": 3155,
                            "Price": 279.7,
                            "Orders": 0,
                            "Flag": null
                        },
                        {
                            "Quantity": 0,
                            "Price": 0,
                            "Orders": 0,
                            "Flag": null
                        },
                        {
                            "Quantity": 0,
                            "Price": 0,
                            "Orders": 0,
                            "Flag": null
                        },
                        {
                            "Quantity": 0,
                            "Price": 0,
                            "Orders": 0,
                            "Flag": null
                        },
                        {
                            "Quantity": 0,
                            "Price": 0,
                            "Orders": 0,
                            "Flag": null
                        }
                    ],
                    "sell": [
                        {
                            "Quantity": 3155,
                            "Price": 279.8,
                            "Orders": 0,
                            "Flag": null
                        },
                        {
                            "Quantity": 0,
                            "Price": 0,
                            "Orders": 0,
                            "Flag": null
                        },
                        {
                            "Quantity": 0,
                            "Price": 0,
                            "Orders": 0,
                            "Flag": null
                        },
                        {
                            "Quantity": 0,
                            "Price": 0,
                            "Orders": 0,
                            "Flag": null
                        },
                        {
                            "Quantity": 0,
                            "Price": 0,
                            "Orders": 0,
                            "Flag": null
                        }
                    ],
                    "The52WeekHigh": 289.2,
                    "The52WeekLow": 0,
                    "ProviderTime": "2026-05-26T23:30:37.050206+05:30",
                    "BrokerReceiveTime": null,
                    "IsHistoryOn": false,
                    "ohlc": {
                        "high": "285.3",
                        "low": "278.4"
                    }
                },
                {
                    "mode": "IQ",
                    "ExchangeToken": "QNGM26",
                    "instrument_token": "66500552748",
                    "tradable": true,
                    "last_price": 2.896,
                    "last_quantity": 7,
                    "average_price": null,
                    "volume": 55,
                    "buy_quantity": 0,
                    "sell_quantity": 0,
                    "ohlc_open": "2.910",
                    "ohlc_high": "2.921",
                    "ohlc_low": "2.882",
                    "ohlc_close": "2.894",
                    "change": "0.002",
                    "buy_price_0": 2.882,
                    "sell_price_0": 2.891,
                    "buy_qty_0": 1,
                    "sell_qty_0": 1,
                    "LastTradeTimeD": "2026-05-27T09:39:04.0716684+05:30",
                    "last_trade_time": "27-05-2026 09:39:04",
                    "oi": 3888,
                    "oi_day_high": null,
                    "oi_day_low": null,
                    "timestamp": "2026-05-27T09:39:04.0716684+05:30",
                    "name": "NATURALGAS",
                    "expiry": "27-05-2026",
                    "exchange": "COMEX",
                    "tradingsymbol": "NATURALGAS 27May2026",
                    "lot_size": "1.000",
                    "lower_circuit": "0",
                    "upper_circuit": "0",
                    "net_change": "0.00",
                    "percentage_change": "0.07",
                    "buy": [],
                    "sell": [],
                    "The52WeekHigh": 4.42,
                    "The52WeekLow": 0,
                    "ProviderTime": "2026-05-27T09:39:04.0717061+05:30",
                    "BrokerReceiveTime": null,
                    "IsHistoryOn": false,
                    "ohlc": {
                        "high": "2.921",
                        "low": "2.882"
                    }
                },
                {
                    "mode": "XL",
                    "ExchangeToken": "44439",
                    "instrument_token": "44439",
                    "tradable": false,
                    "last_price": 104.980003,
                    "last_quantity": null,
                    "average_price": "0",
                    "volume": 2189,
                    "buy_quantity": 0,
                    "sell_quantity": 0,
                    "ohlc_open": "104.98",
                    "ohlc_high": "104.98",
                    "ohlc_low": "104.75",
                    "ohlc_close": "104.980003",
                    "change": null,
                    "buy_price_0": 104.76,
                    "sell_price_0": 104.79,
                    "buy_qty_0": 80,
                    "sell_qty_0": 103,
                    "LastTradeTimeD": "2026-05-26T13:38:51",
                    "last_trade_time": "26-05-2026 13:38:51",
                    "oi": null,
                    "oi_day_high": null,
                    "oi_day_low": null,
                    "timestamp": "2026-05-26T13:38:51",
                    "name": "DGCX",
                    "expiry": "26-05-2026",
                    "exchange": "DGCX",
                    "tradingsymbol": "DGCX 26May2026",
                    "lot_size": "0",
                    "lower_circuit": "0",
                    "upper_circuit": "0",
                    "net_change": "0",
                    "percentage_change": "0",
                    "buy": [],
                    "sell": [],
                    "The52WeekHigh": 0,
                    "The52WeekLow": 0,
                    "ProviderTime": "2026-05-26T13:38:51.5816831+05:30",
                    "BrokerReceiveTime": null,
                    "IsHistoryOn": true,
                    "ohlc": {
                        "high": "104.98",
                        "low": "104.75"
                    }
                }
            ],
            "uniqId": "69df6e21bab8e09015512d21",
            "marketType": "badla",
            "equation": "L1*L3",
            "duty": 15
        }
    }
}